{
  "@context": "https://schema.org",
  "@type": "FAQPage",
  "mainEntity": [
    {
      "@type": "Question",
      "name": "What is included in Landscape Photography Workshop Anglesey Island | Wales?",
      "acceptedAnswer": {
        "@type": "Answer",
        "text": "Summary - Anglesey Photography Workshop Location: Wales - Anglesey Island Dates: Fri 8th May 15:00 - Sun 10th May 14:00, 2026 Duration: 3 Days/2 Nights Participants: Max 4 (1 Car, transport between locations included) Fitness: 2."
      }
    },
    {
      "@type": "Question",
      "name": "What dates are currently listed for Landscape Photography Workshop Anglesey Island | Wales?",
      "acceptedAnswer": {
        "@type": "Answer",
        "text": "Current listed dates include 10 Apr 2026, 8 May 2026, 28 Aug 2026, plus additional listed dates."
      }
    },
    {
      "@type": "Question",
      "name": "Where does Landscape Photography Workshop Anglesey Island | Wales take place?",
      "acceptedAnswer": {
        "@type": "Answer",
        "text": "Landscape Photography Workshop Anglesey Island | Wales is listed with location details for Anglesey on this page."
      }
    },
    {
      "@type": "Question",
      "name": "What experience level is Landscape Photography Workshop Anglesey Island | Wales aimed at?",
      "acceptedAnswer": {
        "@type": "Answer",
        "text": "This is described as suitable for Beginners photographers."
      }
    },
    {
      "@type": "Question",
      "name": "How long is Landscape Photography Workshop Anglesey Island | Wales?",
      "acceptedAnswer": {
        "@type": "Answer",
        "text": "The page describes this as a 3 Days format."
      }
    }
  ],
  "@id": "https://www.alanranger.com/photo-workshops-uk/landscape-photography-workshops-anglesey#faq"
}